wgl.py
wgl-0.4.6.dist-info/METADATA
wgl-0.4.6.dist-info/WHEEL
wgl-0.4.6.dist-info/RECORD
