Metadata-Version: 2.3
Name: wgl
Version: 0.4.6
Summary: Generate random real-world WebGL fingerprint data.
License: MIT
Keywords: wgl,fingerprint,graphics
Author: Vincent Mahan
Author-email: vincemahan@gmail.com
Requires-Python: >=3.9
Classifier: Programming Language :: Python :: 3
Classifier: License :: OSI Approved :: MIT License
Classifier: Operating System :: OS Independent
Project-URL: Documentation, https://pypi.org/project/wgl
Project-URL: Homepage, https://pypi.org/project/wgl
Project-URL: Repository, https://pypi.org/project/wgl#files
